py2secmail/__init__.py
py2secmail/py2secmail.py
py2secmail-0.2.3.dist-info/METADATA
py2secmail-0.2.3.dist-info/WHEEL
py2secmail-0.2.3.dist-info/top_level.txt
py2secmail-0.2.3.dist-info/RECORD
