Metadata-Version: 2.4
Name: Py2SecMail
Version: 0.2.3
Summary: Librairie pour interagir avec l'API 2SecMail pour des emails temporaires
Home-page: https://github.com/alvorks/Py2SecMail
Author: ItsukiPth
Author-email: itsukiche@gmail.com
Classifier: Programming Language :: Python :: 3
Classifier: License :: OSI Approved :: MIT License
Classifier: Operating System :: OS Independent
Requires-Python: >=3.6
Requires-Dist: requests
Dynamic: author
Dynamic: author-email
Dynamic: classifier
Dynamic: description
Dynamic: description-content-type
Dynamic: home-page
Dynamic: requires-dist
Dynamic: requires-python
Dynamic: summary
